report.py
fastreport-0.0.6.dist-info/LICENSE
fastreport-0.0.6.dist-info/METADATA
fastreport-0.0.6.dist-info/WHEEL
fastreport-0.0.6.dist-info/top_level.txt
fastreport-0.0.6.dist-info/RECORD
