Metadata-Version: 2.1
Name: fastreport
Version: 0.0.6
Summary: UNKNOWN
Home-page: https://github.com/kishore-s-gowda/fastreport
Author: Kishore
Author-email: <kishoresshankar@gmail.com>
License: MIT
Keywords: python,regression,classification,algorithm
Platform: UNKNOWN
Classifier: Development Status :: 1 - Planning
Classifier: Intended Audience :: Developers
Classifier: Programming Language :: Python :: 3
Classifier: Operating System :: Unix
Classifier: Operating System :: MacOS :: MacOS X
Classifier: Operating System :: Microsoft :: Windows
